singleCellHaystack/__init__.py
singleCellHaystack/_cluster.py
singleCellHaystack/_data.py
singleCellHaystack/_grid.py
singleCellHaystack/_haystack.py
singleCellHaystack/_kld.py
singleCellHaystack/_plot.py
singleCellHaystack/_pvalue.py
singleCellHaystack/_randomization.py
singleCellHaystack/_tools.py
singleCellHaystack/datasets/toy.h5ad
singleCellHaystack-0.0.5.dist-info/LICENSE
singleCellHaystack-0.0.5.dist-info/METADATA
singleCellHaystack-0.0.5.dist-info/WHEEL
singleCellHaystack-0.0.5.dist-info/top_level.txt
singleCellHaystack-0.0.5.dist-info/RECORD
