Metadata-Version: 2.1
Name: singleCellHaystack
Version: 0.0.5
Summary: A Python implementation of singleCellHaystack.
Author-email: Diego Diez <diego10ruiz@gmail.com>
License: MIT License
Project-URL: Homepage, https://github.com/ddiez/singleCellHaystack-py
Project-URL: Bug Tracker, https://github.com/ddiez/singleCellHaystack-py/issues
Classifier: Programming Language :: Python :: 3
Classifier: License :: OSI Approved :: MIT License
Classifier: Operating System :: OS Independent
Classifier: Topic :: Scientific/Engineering :: Bio-Informatics
Classifier: Intended Audience :: Science/Research
Classifier: Development Status :: 4 - Beta
Requires-Python: >=3.7
License-File: LICENSE
Requires-Dist: numpy
Requires-Dist: scipy
Requires-Dist: scikit-learn
Requires-Dist: anndata
Requires-Dist: scanpy
Requires-Dist: pandas
Requires-Dist: tqdm
